booth.v
module booth(
	// control signals
	input clk, load, reset,
	input [15:0] M,
	input [15:0] Q,
	output reg [31:0] P

    );
	 
	 reg [15:0] A = 15'b0;
	 reg Q_minus_one = 0;
	 reg [15:0] Q_temp = 15'b0;
	 reg [15:0] M_temp = 15'b0;
	 reg [4:0] cnt = 0;
	 
	 
	 
	 always @ (posedge clk)
	 begin
		if (reset == 1)
		begin
			A = 15'b0;		//reset values
			Q_minus_one = 0;
			P = 31'b0;
			Q_temp = 15'b0;
			M_temp = 15'b0;
			cnt = 0;

		end

		else if (load == 1)
		begin
			Q_temp =  Q;
			M_temp =  M;
		end

		else if((Q_temp[0] == Q_minus_one ) && (cnt < 16))
		begin
			Q_minus_one = Q_temp[0];
			Q_temp = {A[0],Q_temp[15:1]};				// right shift Q							
			A = {A[15],A[15:1]};					// right shift A	
		    cnt = cnt + 1'b1;					
		end
		else if((Q_temp[0] == 0 && Q_minus_one == 1)  && (cnt < 16))
		begin
			A = A + M_temp;
			Q_minus_one = Q_temp[0];
			Q_temp = {A[0],Q_temp[15:1]};			// right shift Q
			A = {A[15],A[15:1]};					// right shift A
			cnt = cnt + 1'b1;
		end
		else if((Q_temp[0] == 1 && Q_minus_one == 0)  && (cnt < 16))
		begin
			A = A - M_temp;
			Q_minus_one = Q_temp[0];
			Q_temp = {A[0],Q_temp[15:1]};				// right shift Q
			A = {A[15],A[15:1]};					// right shift A
			cnt = cnt + 1'b1;
		end
		P = {A, Q_temp};
		
	 end

endmodule

testBenches.v

module or_tb;
reg clk, rst;
    reg [15:0] A;
    reg [15:0] B;
    wire [15:0] out;

    ornr uut(.clk(clk), .A(A), .B(B), .outputreg(out));
    integer i;

    initial begin
        clk = 0;
        repeat (200) #1 clk = ~clk;
    end

    initial begin
        rst = 0;
        #1 rst = ~rst;
    end

    initial begin
    A = 23;
    B = 101; 

    #1 $display("\n%b\n%b\n%b", A, B, out);
    end
endmodule


module or1bit_tb;
reg clk, rst;
    reg A;
    reg B;
    wire out;

    or1bit uut(.clk(clk), .A(A), .B(B), .outputreg(out));
    integer i;

    initial begin
        clk = 0;
        repeat (200) #1 clk = ~clk;
    end

    initial begin
        rst = 0;
        #1 rst = ~rst;
    end

    initial begin
    A = 0;
    B = 0; 

    #1 $display("\n%b\n%b\n%b", A, B, out);
    end
endmodule

module and_tb;
reg clk, rst;
    reg [15:0] A;
    reg [15:0] B;
    wire [15:0] out;

    and1 uut(.clk(clk), .A(A), .B(B), .outputreg(out));
    integer i;

    initial begin
        clk = 0;
        repeat (200) #1 clk = ~clk;
    end

    initial begin
        rst = 0;
        #1 rst = ~rst;
    end

    initial begin
    A = 23;
    B = 101; 

    #1 $display("\n%b\n%b\n%b", A, B, out);
    end
endmodule

module and1bit_tb;
reg clk, rst;
    reg A;
    reg B;
    wire out;

    and1bit uut(.clk(clk), .A(A), .B(B), .outputreg(out));
    integer i;

    initial begin
        clk = 0;
        repeat (200) #1 clk = ~clk;
    end

    initial begin
        rst = 0;
        #1 rst = ~rst;
    end

    initial begin
    A = 1;
    B = 1; 

    #1 $display("\n%b\n%b\n%b", A, B, out);
    end
endmodule

module logicalshifter_tb;
    reg clk, rst;
    reg [15:0] A;
    wire [15:0] B;

    logicalshifter uut(.clk(clk), .rst(rst), .s(2'b01), .inputreg(A), .outputreg(B));
    integer i;

    initial begin
        clk = 0;
        repeat (200) #1 clk = ~clk;
    end

    initial begin
        rst = 0;
        #1 rst = ~rst;
    end

    initial begin 
    A = 0;
    for (i = 0; i < 15; i = i + 1) begin
        //#1 A[i] = 0;
        #1 $display("\t%b\t%b", A, B);

        //#1 A[i] = 1;
        //#1 $display("\t%b\t%b", A, B);
    end
  end
endmodule

module arithmeticshifter_tb;
    reg clk, rst;
    reg [15:0] A;
    wire [15:0] B;

    arithmeticshifter uut(.clk(clk), .rst(rst), .s(2'b10), .inputreg(A), .outputreg(B));
    integer i;

    initial begin
        clk = 0;
        repeat (200) #1 clk = ~clk;
    end

    initial begin
        rst = 0;
        #1 rst = ~rst;
    end

    initial begin 
    A = 2**15;
    for (i = 0; i < 15; i = i + 1) begin
        #1 A[i] = 0;
        #1 $display("\t%b\t%b", A, B);

        #1 A[i] = 1;
        #1 $display("\t%b\t%b", A, B);
        end
    end
endmodule


module xor_tb;
reg clk, rst;
    reg [15:0] A;
    reg [15:0] B;
    wire [15:0] out;

    xor1 uut(.clk(clk), .A(A), .B(B), .outputreg(out));
    integer i;

    initial begin
        clk = 0;
        repeat (200) #1 clk = ~clk;
    end

    initial begin
        rst = 0;
        #1 rst = ~rst;
    end

    initial begin
    A = 23;
    B = 101; 

    #1 $display("\n%b\n%b\n%b", A, B, out);
    end
endmodule


module RCA_tb;
reg clk, rst;
    reg [15:0] A;
    reg [15:0] B;
    wire cout;
    wire [15:0] out;

    RCA uut(.a(A), .b(B), .cin(1'b0), .cout(cout), .sum(out));
    integer i;

    initial begin
        clk = 0;
        repeat (200) #1 clk = ~clk;
    end

    initial begin
        rst = 0;
        #1 rst = ~rst;
    end

    initial begin
    A = 447;
    B = 38; 

    #1 $display("\n%b\n%b\n%d", A, B, out);
    end
endmodule



module RCAD_tb;
reg clk, rst, ld;
    reg [15:0] A;
    reg [15:0] B;
    wire cout;
    wire [15:0] out;

    RCAD uut(.a(B), .b(A), .cin(1'b0), .cout(cout), .sum(out));
    integer i;

    initial begin
        clk = 0;
        repeat (200) #1 clk = ~clk;
    end

    initial begin
        rst = 0;
        #1 rst = ~rst;
    end

    initial begin
        A = 447;
        B = 38; 
        #1 $display("\n%b\n%b\n%b", A, B, out);
        end 


endmodule


module booth_tb;

	reg clk;
	reg load;
	reg reset;
	reg [15:0] M;
	reg [15:0] Q;

	wire [31:0] P;

	 booth uut (
		.clk(clk), 
		.load(load), 
		.reset(reset), 
		.M(M), 
		.Q(Q), 
		.P(P)
	);
	
	always
		#10 clk = ~clk;
  
  initial 
    begin
      	$dumpfile("design.vcd");
        $dumpvars(0,booth_tb );
      	$monitor ( $time, " Q = %b, M = %b, P = %b, cnt = %d              A = %b , Q_temp = %b",  Q, M, P, uut.cnt, uut.A, uut.Q_temp);
    end
	
	initial begin
		clk = 0;
		load = 0;
		reset = 1'b1;
		M = 931;
		Q = 788;
		#20;
		load = 1;
		reset = 1'b0;
		#20;
		load = 0;
		#500
		M = 442;
		Q = 131;
        #1200 $finish;

	end
      
endmodule


module division_tb;

    reg [15:0] divisor;
    reg [15:0] dividend;
    reg clk;
    reg load;
    reg rst;

    wire [15:0] result;
    wire [15:0] remainder;

    division uut (
        .clk(clk),
        .ld(load),
        .rst(rst),
        .a(divisor),
        .b(dividend),
        .r(remainder),
        .q(result)
    );
    
    always #5 clk = ~clk; // Toggle the clock every 5 time units

    initial begin
        clk = 0;
        load = 0;
        rst = 1;
        divisor = 3473;
        dividend = 147;
        #20; // Wait for a brief period
        rst = 0; // De-assert reset
        // #5; // Wait for a brief period
        load = 1; // Assert load
        #20; // Wait for a brief period
        load = 0; // De-assert load
        #1200 $finish; // Finish simulation after a long period
    end

    initial begin
        $monitor("Divisor: %b, Dividend: %b, Remainder: %d, Result: %d, AQ: %b, R=%b,  Count:%d", divisor, dividend, remainder, result, uut.AQ, uut.R, uut.R);
    end

endmodule





module alu_tb;

    reg clk, rst;
    reg [15:0] A, B;
    reg [3:0] select;
    wire [15:0] result;

    ALU xd(.clk(clk), .rst(rst), .A(A), .B(B), .select(select), .result(result));

    localparam ClOCKCYCLES=500;
    localparam CLKPERIOD=10;

    initial begin
        clk = 0;
        repeat(ClOCKCYCLES*2) #(CLKPERIOD/2) clk = ~clk;
    end

    integer i;

    initial begin
        A = 447;
        B = 38;
        rst = 1;
        #10 rst = 0;
        select = 4'b0;
        for(i = 0; i < 11; i = i + 1) begin
            select = i;
            #(CLKPERIOD * 15) $display("A = %d A = %b | B = %d B = %b | Result = %d Result %b | Operation : %b", A, A, B, B, result, result, select);
        end
        $display("\n");
        
        A = 194;
        B = 69;
        rst = 1;
        #10 rst = 0;
        select = 4'b0;
        for(i = 0; i < 11; i = i + 1) begin
            #10
            select = i;
            #(CLKPERIOD * 15) $display("A = %d A = %b | B = %d B = %b | Result = %d Result %b | Operation : %b", A, A, B, B, result, result, select);
        end
        $display("\n");

        A = 268;
        B = 33;
        rst = 1;
        #10 rst = ~rst;
        select = 4'b0;
        #10
        for(i = 0; i < 11; i = i + 1) begin
            #10
            select = i;
            #(CLKPERIOD * 15) $display("A = %d A = %b | B = %d B = %b | Result = %d Result %b | Operation : %b", A, A, B, B, result, result, select);
        end
        $display("\n");

    end

endmodule

design.vcd
$date
	Wed Apr 17 21:03:56 2024
$end
$version
	ModelSim Version 2020.1
$end
$timescale
	1ps
$end

$scope module booth_tb $end
$var reg 1 ! clk $end
$var reg 1 " load $end
$var reg 1 # reset $end
$var reg 16 $ M [15:0] $end
$var reg 16 % Q [15:0] $end
$var wire 1 & P [31] $end
$var wire 1 ' P [30] $end
$var wire 1 ( P [29] $end
$var wire 1 ) P [28] $end
$var wire 1 * P [27] $end
$var wire 1 + P [26] $end
$var wire 1 , P [25] $end
$var wire 1 - P [24] $end
$var wire 1 . P [23] $end
$var wire 1 / P [22] $end
$var wire 1 0 P [21] $end
$var wire 1 1 P [20] $end
$var wire 1 2 P [19] $end
$var wire 1 3 P [18] $end
$var wire 1 4 P [17] $end
$var wire 1 5 P [16] $end
$var wire 1 6 P [15] $end
$var wire 1 7 P [14] $end
$var wire 1 8 P [13] $end
$var wire 1 9 P [12] $end
$var wire 1 : P [11] $end
$var wire 1 ; P [10] $end
$var wire 1 < P [9] $end
$var wire 1 = P [8] $end
$var wire 1 > P [7] $end
$var wire 1 ? P [6] $end
$var wire 1 @ P [5] $end
$var wire 1 A P [4] $end
$var wire 1 B P [3] $end
$var wire 1 C P [2] $end
$var wire 1 D P [1] $end
$var wire 1 E P [0] $end

$scope module uut $end
$var wire 1 F clk $end
$var wire 1 G load $end
$var wire 1 H reset $end
$var wire 1 I M [15] $end
$var wire 1 J M [14] $end
$var wire 1 K M [13] $end
$var wire 1 L M [12] $end
$var wire 1 M M [11] $end
$var wire 1 N M [10] $end
$var wire 1 O M [9] $end
$var wire 1 P M [8] $end
$var wire 1 Q M [7] $end
$var wire 1 R M [6] $end
$var wire 1 S M [5] $end
$var wire 1 T M [4] $end
$var wire 1 U M [3] $end
$var wire 1 V M [2] $end
$var wire 1 W M [1] $end
$var wire 1 X M [0] $end
$var wire 1 Y Q [15] $end
$var wire 1 Z Q [14] $end
$var wire 1 [ Q [13] $end
$var wire 1 \ Q [12] $end
$var wire 1 ] Q [11] $end
$var wire 1 ^ Q [10] $end
$var wire 1 _ Q [9] $end
$var wire 1 ` Q [8] $end
$var wire 1 a Q [7] $end
$var wire 1 b Q [6] $end
$var wire 1 c Q [5] $end
$var wire 1 d Q [4] $end
$var wire 1 e Q [3] $end
$var wire 1 f Q [2] $end
$var wire 1 g Q [1] $end
$var wire 1 h Q [0] $end
$var reg 32 i P [31:0] $end
$var reg 16 j A [15:0] $end
$var reg 1 k Q_minus_one $end
$var reg 16 l Q_temp [15:0] $end
$var reg 16 m M_temp [15:0] $end
$var reg 5 n cnt [4:0] $end
$upscope $end
$upscope $end
$enddefinitions $end
#0
$dumpvars
0!
0"
1#
b1110100011 $
b1100010100 %
bx i
b0 j
0k
b0 l
b0 m
b0 n
xE
xD
xC
xB
xA
x@
x?
x>
x=
x<
x;
x:
x9
x8
x7
x6
x5
x4
x3
x2
x1
x0
x/
x.
x-
x,
x+
x*
x)
x(
x'
x&
0h
0g
1f
0e
1d
0c
0b
0a
1`
1_
0^
0]
0\
0[
0Z
0Y
1X
1W
0V
0U
0T
1S
0R
1Q
1P
1O
0N
0M
0L
0K
0J
0I
1H
0G
0F
$end
#10
1!
1F
b0 i
0E
0D
0C
0B
0A
0@
0?
0>
0=
0<
0;
0:
09
08
07
06
05
04
03
02
01
00
0/
0.
0-
0,
0+
0*
0)
0(
0'
0&
#20
1"
0#
0!
1G
0H
0F
#30
1!
1F
b1100010100 l
b1110100011 m
b1100010100 i
1C
1A
1=
1<
#40
0"
0!
0G
0F
#50
1!
1F
b110001010 l
b1 n
b110001010 i
1D
0C
1B
0A
1>
0<
#60
0!
0F
#70
1!
1F
b11000101 l
b10 n
b11000101 i
1E
0D
1C
0B
1?
0=
#80
0!
0F
#90
1!
1F
b1111110001011101 j
1k
b1000000001100010 l
b1111111000101110 j
b11 n
b11111110001011101000000001100010 i
0E
1D
0C
1@
0>
16
14
13
12
10
1,
1+
1*
1)
1(
1'
1&
#100
0!
0F
#110
1!
1F
b111010001 j
0k
b1100000000110001 l
b11101000 j
b100 n
b111010001100000000110001 i
1E
0D
1A
0?
17
04
03
1/
1.
0,
0+
0*
0)
0(
0'
0&
#120
0!
0F
#130
1!
1F
b1111110101000101 j
1k
b1110000000011000 l
b1111111010100010 j
b101 n
b11111110101000101110000000011000 i
0E
1B
0@
18
14
02
0/
1,
1+
1*
1)
1(
1'
1&
#140
0!
0F
#150
1!
1F
b1001000101 j
0k
b1111000000001100 l
b100100010 j
b110 n
b1001000101111000000001100 i
1C
0A
19
0.
1-
0,
0+
0*
0)
0(
0'
0&
#160
0!
0F
#170
1!
1F
b111100000000110 l
b10010001 j
b111 n
b100100010111100000000110 i
1D
0B
1:
06
15
04
11
00
1.
0-
#180
0!
0F
#190
1!
1F
b1011110000000011 l
b1001000 j
b1000 n
b10010001011110000000011 i
1E
0C
1;
07
16
05
12
01
1/
0.
#200
0!
0F
#210
1!
1F
b1111110010100101 j
1k
b1101111000000001 l
b1111111001010010 j
b1001 n
b11111110010100101101111000000001 i
0D
1<
08
17
14
02
11
1,
1+
1*
1)
1(
1'
1&
#220
0!
0F
#230
1!
1F
b110111100000000 l
b1111111100101001 j
b1010 n
b11111111001010010110111100000000 i
0E
1=
09
18
06
15
04
12
01
10
0/
1-
#240
0!
0F
#250
1!
1F
b1011001100 j
0k
b11011110000000 l
b101100110 j
b1011 n
b1011001100011011110000000 i
1>
0:
19
07
05
14
13
02
1/
0,
0+
0*
0)
0(
0'
0&
#260
0!
0F
#270
1!
1F
b1101111000000 l
b10110011 j
b1100 n
b101100110001101111000000 i
1?
0;
1:
08
15
03
11
0/
1.
0-
#280
0!
0F
#290
1!
1F
b1000110111100000 l
b1011001 j
b1101 n
b10110011000110111100000 i
1@
0<
1;
09
16
04
12
00
1/
0.
#300
0!
0F
#310
1!
1F
b1100011011110000 l
b101100 j
b1110 n
b1011001100011011110000 i
1A
0=
1<
0:
17
05
13
01
10
0/
#320
0!
0F
#330
1!
1F
b110001101111000 l
b10110 j
b1111 n
b101100110001101111000 i
1B
0>
1=
0;
18
06
14
02
11
00
#340
0!
0F
#350
1!
1F
b11000110111100 l
b1011 j
b10000 n
b10110011000110111100 i
1C
0?
1>
0<
19
07
15
03
12
01
